ddmail_openpgp_keyhandler/__init__.py
ddmail_openpgp_keyhandler/application.py
ddmail_openpgp_keyhandler-0.0.3.dist-info/METADATA
ddmail_openpgp_keyhandler-0.0.3.dist-info/WHEEL
ddmail_openpgp_keyhandler-0.0.3.dist-info/licenses/LICENSE
ddmail_openpgp_keyhandler-0.0.3.dist-info/RECORD
